MANIFEST.in
setup.py
jsroutes/__init__.py
jsroutes/models.py
jsroutes/tests.py
jsroutes/urls.py
jsroutes/utils.py
jsroutes/views.py
jsroutes.egg-info/PKG-INFO
jsroutes.egg-info/SOURCES.txt
jsroutes.egg-info/dependency_links.txt
jsroutes.egg-info/not-zip-safe
jsroutes.egg-info/requires.txt
jsroutes.egg-info/top_level.txt
jsroutes/management/__init__.py
jsroutes/management/commands/__init__.py
jsroutes/management/commands/generate_jsroutes.py
jsroutes/templates/jsroutes.js