Metadata-Version: 1.0
Name: jsroutes
Version: 0.1.5
Summary: use 'reverse' from javascript
Home-page: UNKNOWN
Author: Viktor Kotseruba
Author-email: barbuzaster@gmail.com
License: MIT
Keywords: web django
Platform: UNKNOWN
